secretscraper/__init__.py
secretscraper/cmdline.py
secretscraper/config/__init__.py
secretscraper/config/settings.yml
secretscraper/coroutinue.py
secretscraper/crawler.py
secretscraper/entity.py
secretscraper/exception.py
secretscraper/facade.py
secretscraper/filter.py
secretscraper/handler.py
secretscraper/log.py
secretscraper/output_formatter.py
secretscraper/scanner.py
secretscraper/urlparser.py
secretscraper/util.py
secretscraper-1.4.1.dist-info/LICENSE
secretscraper-1.4.1.dist-info/METADATA
secretscraper-1.4.1.dist-info/WHEEL
secretscraper-1.4.1.dist-info/entry_points.txt
secretscraper-1.4.1.dist-info/RECORD
