Metadata-Version: 2.1
Name: secretscraper
Version: 1.4.1
Summary: SecretScraper is a web scraper tool that can scrape the content through target websites and extract secret information via regular expression.
License: MIT
Author: Padishah
Author-email: straystrayer@gmail.com
Requires-Python: >=3.9,<4.0
Classifier: License :: OSI Approved :: MIT License
Classifier: Operating System :: OS Independent
Classifier: Programming Language :: Python :: 3
Classifier: Programming Language :: Python :: 3.9
Classifier: Programming Language :: Python :: 3.10
Classifier: Programming Language :: Python :: 3.11
Classifier: Programming Language :: Python :: 3.12
Requires-Dist: aiocache (>=0.12.2,<0.13.0)
Requires-Dist: aiohttp (>=3.9.4,<4.0.0)
Requires-Dist: bs4 (>=0.0.2,<0.0.3)
Requires-Dist: click (>=8.1.3,<9.0.0)
Requires-Dist: dynaconf (>=3.1.12,<4.0.0)
Requires-Dist: httpx[socks] (>=0.27.0,<0.28.0)
Requires-Dist: hyperscan (>=0.7.0,<0.8.0) ; python_version >= "3.10" and python_version < "4.0" and sys_platform == "darwin"
Requires-Dist: hyperscan (>=0.7.0,<0.8.0) ; python_version >= "3.10" and python_version < "4.0" and sys_platform == "linux"
Requires-Dist: hyperscan (>=0.7.7,<0.8.0) ; python_version >= "3.11" and python_version < "4.0" and sys_platform == "darwin"
Requires-Dist: hyperscan (>=0.7.7,<0.8.0) ; python_version >= "3.11" and python_version < "4.0" and sys_platform == "linux"
Requires-Dist: tldextract (>=5.1.2,<6.0.0)
